chATLAS_Benchmark/__init__.py
chATLAS_Benchmark/_version.py
chATLAS_Benchmark/Generation/__init__.py
chATLAS_Benchmark/Generation/extra_validation.py
chATLAS_Benchmark/Generation/extra_validation_prompts.py
chATLAS_Benchmark/Generation/gen_qa_pairs.py
chATLAS_Benchmark/Generation/gen_simple_qa_pairs.py
chATLAS_Benchmark/test_utils/__init__.py
chATLAS_Benchmark/test_utils/database_utils.py
chATLAS_Benchmark/tests/AnswerCorrect.py
chATLAS_Benchmark/tests/DocumentMatch.py
chATLAS_Benchmark/tests/LexicalMetrics.py
chATLAS_Benchmark/tests/__init__.py
chATLAS_Benchmark/tests/semanticSimilarity.py
chATLAS_Benchmark/tests/test_benchmark_metrics.py
chatlas_benchmark-0.0.10.dist-info/licenses/LICENSE
chatlas_benchmark-0.0.10.dist-info/METADATA
chatlas_benchmark-0.0.10.dist-info/WHEEL
chatlas_benchmark-0.0.10.dist-info/top_level.txt
chatlas_benchmark-0.0.10.dist-info/RECORD
