Metadata-Version: 2.4
Name: chATLAS_Benchmark
Version: 0.0.10
Summary: A Python package for LLM and RAG testing in high-energy physics applications (Originally for ATLAS in the chATLAS project).
Author-email: Ben Elliot <Ben.Elliot27@outlook.com>
License: Apache-2.0
Project-URL: Homepage, https://gitlab.cern.ch/belliot/chatlas-packages/
Project-URL: Documentation, https://chatlas-packages.docs.cern.ch/chATLAS_Benchmark/
Classifier: Programming Language :: Python :: 3
Classifier: License :: OSI Approved :: Apache Software License
Classifier: Operating System :: OS Independent
Requires-Python: >=3.11
License-File: LICENSE
Requires-Dist: numpy~=1.26.4
Requires-Dist: pandas~=2.2.3
Requires-Dist: SQLAlchemy~=2.0.35
Requires-Dist: nltk~=3.9.1
Requires-Dist: torch~=2.2.1; sys_platform == "darwin" and platform_machine == "x86_64"
Requires-Dist: sentence_transformers~=3.2.0
Requires-Dist: pathlib
Requires-Dist: dataclasses; python_version < "3.7"
Requires-Dist: openai
Requires-Dist: pytest
Dynamic: license-file
